cbv_inspect/__init__.py
cbv_inspect/apps.py
cbv_inspect/decorators.py
cbv_inspect/middleware.py
cbv_inspect/mixins.py
cbv_inspect/utils.py
cbv_inspect/views.py
cbv_inspect/templates/cbv_inspect/toolbar.html
django_cbv_inspect-0.2.1.dist-info/LICENSE
django_cbv_inspect-0.2.1.dist-info/METADATA
django_cbv_inspect-0.2.1.dist-info/WHEEL
django_cbv_inspect-0.2.1.dist-info/top_level.txt
django_cbv_inspect-0.2.1.dist-info/RECORD
