Metadata-Version: 2.1
Name: django-cbv-inspect
Version: 0.2.1
Summary: A tool to inspect Django class-based views.
Author-email: Sangeeta Jadoonanan <sjbitcode@gmail.com>
License: MIT
Project-URL: Homepage, https://github.com/sjbitcode/django-cbv-inspect
Project-URL: Download, https://pypi.org/project/django-cbv-inspect
Keywords: python,django
Classifier: Environment :: Web Environment
Classifier: Framework :: Django
Classifier: Framework :: Django :: 3.2
Classifier: Framework :: Django :: 4.0
Classifier: Framework :: Django :: 4.1
Classifier: Programming Language :: Python :: 3
Classifier: Programming Language :: Python :: 3 :: Only
Classifier: Programming Language :: Python :: 3.7
Classifier: Programming Language :: Python :: 3.8
Classifier: Programming Language :: Python :: 3.9
Classifier: Programming Language :: Python :: 3.10
Classifier: Programming Language :: Python :: 3.11
Classifier: Intended Audience :: Developers
Classifier: Programming Language :: Python :: 3
Classifier: License :: OSI Approved :: MIT License
Classifier: Topic :: Software Development :: Libraries :: Python Modules
Requires-Python: >=3.7
License-File: LICENSE
Requires-Dist: Django (>=3.2)
